workflows/__init__.py
workflows/__main__.py
workflows/_vendor/gitignore/.github/PULL_REQUEST_TEMPLATE.md
workflows/_vendor/gitignore/.travis.yml
workflows/_vendor/gitignore/Actionscript.gitignore
workflows/_vendor/gitignore/Ada.gitignore
workflows/_vendor/gitignore/Agda.gitignore
workflows/_vendor/gitignore/Android.gitignore
workflows/_vendor/gitignore/AppEngine.gitignore
workflows/_vendor/gitignore/AppceleratorTitanium.gitignore
workflows/_vendor/gitignore/ArchLinuxPackages.gitignore
workflows/_vendor/gitignore/Autotools.gitignore
workflows/_vendor/gitignore/C++.gitignore
workflows/_vendor/gitignore/C.gitignore
workflows/_vendor/gitignore/CFWheels.gitignore
workflows/_vendor/gitignore/CMake.gitignore
workflows/_vendor/gitignore/CONTRIBUTING.md
workflows/_vendor/gitignore/CUDA.gitignore
workflows/_vendor/gitignore/CakePHP.gitignore
workflows/_vendor/gitignore/ChefCookbook.gitignore
workflows/_vendor/gitignore/CodeIgniter.gitignore
workflows/_vendor/gitignore/CommonLisp.gitignore
workflows/_vendor/gitignore/Composer.gitignore
workflows/_vendor/gitignore/Concrete5.gitignore
workflows/_vendor/gitignore/Coq.gitignore
workflows/_vendor/gitignore/CraftCMS.gitignore
workflows/_vendor/gitignore/D.gitignore
workflows/_vendor/gitignore/DM.gitignore
workflows/_vendor/gitignore/Dart.gitignore
workflows/_vendor/gitignore/Delphi.gitignore
workflows/_vendor/gitignore/Drupal.gitignore
workflows/_vendor/gitignore/EPiServer.gitignore
workflows/_vendor/gitignore/Eagle.gitignore
workflows/_vendor/gitignore/Elisp.gitignore
workflows/_vendor/gitignore/Elixir.gitignore
workflows/_vendor/gitignore/Elm.gitignore
workflows/_vendor/gitignore/Erlang.gitignore
workflows/_vendor/gitignore/ExpressionEngine.gitignore
workflows/_vendor/gitignore/ExtJs.gitignore
workflows/_vendor/gitignore/Fancy.gitignore
workflows/_vendor/gitignore/Finale.gitignore
workflows/_vendor/gitignore/ForceDotCom.gitignore
workflows/_vendor/gitignore/FuelPHP.gitignore
workflows/_vendor/gitignore/GWT.gitignore
proman_workflows-0.1.0a8.dist-info/entry_points.txt
proman_workflows-0.1.0a8.dist-info/LICENSE
proman_workflows-0.1.0a8.dist-info/WHEEL
proman_workflows-0.1.0a8.dist-info/METADATA
proman_workflows-0.1.0a8.dist-info/RECORD
