Metadata-Version: 2.1
Name: proman-workflows
Version: 0.1.0a8
Summary: Task-runner for project automation.
Home-page: https://github.com/python-protools/proman-workflows
License: AGPL-3.0-or-later
Keywords: project management
Author: Jesse P. Johnson
Author-email: jpj6652@gmail.com
Requires-Python: >=3.6.2,<4.0.0
Classifier: Intended Audience :: Developers
Classifier: License :: OSI Approved :: GNU Affero General Public License v3 or later (AGPLv3+)
Classifier: Programming Language :: Python :: 3
Classifier: Programming Language :: Python :: 3.10
Classifier: Programming Language :: Python :: 3.6
Classifier: Programming Language :: Python :: 3.7
Classifier: Programming Language :: Python :: 3.8
Classifier: Programming Language :: Python :: 3.9
Provides-Extra: briefcase
Provides-Extra: python
Provides-Extra: shell
Requires-Dist: PyInputPlus (>=0.2.12,<0.3.0)
Requires-Dist: SecretStorage (>=3.3.1,<4.0.0); sys_platform == "linux"
Requires-Dist: cached-property (>=1.5.2,<2.0.0); python_version >= "3.7" and python_version < "3.8"
Requires-Dist: compendium (>=0.1.1-alpha.0,<0.2.0)
Requires-Dist: invoke (>=1.5.0,<2.0.0)
Requires-Dist: keyring (>=23.2.1,<24.0.0)
Requires-Dist: proman-common (>=0.1.1-alpha.1,<0.2.0)
Requires-Dist: pygit2 (>=1.7,<2.0)
Requires-Dist: python-gnupg (>=0.4.7,<0.5.0)
Requires-Dist: stevedore (>=3.4.0,<4.0.0)
